{
	"configurations" : 
	[
		{
			"directories" : 
			[
				{
					"build" : ".",
					"jsonFile" : "directory-.-Debug-d0094a50bb2071803777.json",
					"minimumCMakeVersion" : 
					{
						"string" : "3.10"
					},
					"projectIndex" : 0,
					"source" : ".",
					"targetIndexes" : 
					[
						0,
						1,
						2,
						3,
						4,
						5
					]
				}
			],
			"name" : "Debug",
			"projects" : 
			[
				{
					"directoryIndexes" : 
					[
						0
					],
					"name" : "Composite",
					"targetIndexes" : 
					[
						0,
						1,
						2,
						3,
						4,
						5
					]
				}
			],
			"targets" : 
			[
				{
					"directoryIndex" : 0,
					"id" : "ALL_BUILD::@6890427a1f51a3e7e1df",
					"jsonFile" : "target-ALL_BUILD-Debug-907168c5d66c521f6af6.json",
					"name" : "ALL_BUILD",
					"projectIndex" : 0
				},
				{
					"directoryIndex" : 0,
					"id" : "Composite::@6890427a1f51a3e7e1df",
					"jsonFile" : "target-Composite-Debug-f2e0d662a1153ff349f7.json",
					"name" : "Composite",
					"projectIndex" : 0
				},
				{
					"directoryIndex" : 0,
					"id" : "ZERO_CHECK::@6890427a1f51a3e7e1df",
					"jsonFile" : "target-ZERO_CHECK-Debug-467f88993c7cd49d7801.json",
					"name" : "ZERO_CHECK",
					"projectIndex" : 0
				},
				{
					"directoryIndex" : 0,
					"id" : "glad::@6890427a1f51a3e7e1df",
					"jsonFile" : "target-glad-Debug-8e4ec92a6e6c85d86f71.json",
					"name" : "glad",
					"projectIndex" : 0
				},
				{
					"directoryIndex" : 0,
					"id" : "imgui::@6890427a1f51a3e7e1df",
					"jsonFile" : "target-imgui-Debug-151a384140b9e9a6b51b.json",
					"name" : "imgui",
					"projectIndex" : 0
				},
				{
					"directoryIndex" : 0,
					"id" : "imnodeflow::@6890427a1f51a3e7e1df",
					"jsonFile" : "target-imnodeflow-Debug-c18f922f92a51840c10c.json",
					"name" : "imnodeflow",
					"projectIndex" : 0
				}
			]
		},
		{
			"directories" : 
			[
				{
					"build" : ".",
					"jsonFile" : "directory-.-Release-d0094a50bb2071803777.json",
					"minimumCMakeVersion" : 
					{
						"string" : "3.10"
					},
					"projectIndex" : 0,
					"source" : ".",
					"targetIndexes" : 
					[
						0,
						1,
						2,
						3,
						4,
						5
					]
				}
			],
			"name" : "Release",
			"projects" : 
			[
				{
					"directoryIndexes" : 
					[
						0
					],
					"name" : "Composite",
					"targetIndexes" : 
					[
						0,
						1,
						2,
						3,
						4,
						5
					]
				}
			],
			"targets" : 
			[
				{
					"directoryIndex" : 0,
					"id" : "ALL_BUILD::@6890427a1f51a3e7e1df",
					"jsonFile" : "target-ALL_BUILD-Release-907168c5d66c521f6af6.json",
					"name" : "ALL_BUILD",
					"projectIndex" : 0
				},
				{
					"directoryIndex" : 0,
					"id" : "Composite::@6890427a1f51a3e7e1df",
					"jsonFile" : "target-Composite-Release-cc49d2c282a8854918d8.json",
					"name" : "Composite",
					"projectIndex" : 0
				},
				{
					"directoryIndex" : 0,
					"id" : "ZERO_CHECK::@6890427a1f51a3e7e1df",
					"jsonFile" : "target-ZERO_CHECK-Release-467f88993c7cd49d7801.json",
					"name" : "ZERO_CHECK",
					"projectIndex" : 0
				},
				{
					"directoryIndex" : 0,
					"id" : "glad::@6890427a1f51a3e7e1df",
					"jsonFile" : "target-glad-Release-2e72fc126378d220a4e0.json",
					"name" : "glad",
					"projectIndex" : 0
				},
				{
					"directoryIndex" : 0,
					"id" : "imgui::@6890427a1f51a3e7e1df",
					"jsonFile" : "target-imgui-Release-9de8c3e73889130bb007.json",
					"name" : "imgui",
					"projectIndex" : 0
				},
				{
					"directoryIndex" : 0,
					"id" : "imnodeflow::@6890427a1f51a3e7e1df",
					"jsonFile" : "target-imnodeflow-Release-0228c440cbe4c753c59e.json",
					"name" : "imnodeflow",
					"projectIndex" : 0
				}
			]
		},
		{
			"directories" : 
			[
				{
					"build" : ".",
					"jsonFile" : "directory-.-MinSizeRel-d0094a50bb2071803777.json",
					"minimumCMakeVersion" : 
					{
						"string" : "3.10"
					},
					"projectIndex" : 0,
					"source" : ".",
					"targetIndexes" : 
					[
						0,
						1,
						2,
						3,
						4,
						5
					]
				}
			],
			"name" : "MinSizeRel",
			"projects" : 
			[
				{
					"directoryIndexes" : 
					[
						0
					],
					"name" : "Composite",
					"targetIndexes" : 
					[
						0,
						1,
						2,
						3,
						4,
						5
					]
				}
			],
			"targets" : 
			[
				{
					"directoryIndex" : 0,
					"id" : "ALL_BUILD::@6890427a1f51a3e7e1df",
					"jsonFile" : "target-ALL_BUILD-MinSizeRel-907168c5d66c521f6af6.json",
					"name" : "ALL_BUILD",
					"projectIndex" : 0
				},
				{
					"directoryIndex" : 0,
					"id" : "Composite::@6890427a1f51a3e7e1df",
					"jsonFile" : "target-Composite-MinSizeRel-4d062b1fab00ca8368c3.json",
					"name" : "Composite",
					"projectIndex" : 0
				},
				{
					"directoryIndex" : 0,
					"id" : "ZERO_CHECK::@6890427a1f51a3e7e1df",
					"jsonFile" : "target-ZERO_CHECK-MinSizeRel-467f88993c7cd49d7801.json",
					"name" : "ZERO_CHECK",
					"projectIndex" : 0
				},
				{
					"directoryIndex" : 0,
					"id" : "glad::@6890427a1f51a3e7e1df",
					"jsonFile" : "target-glad-MinSizeRel-3b6d741c4dd01d8f0bff.json",
					"name" : "glad",
					"projectIndex" : 0
				},
				{
					"directoryIndex" : 0,
					"id" : "imgui::@6890427a1f51a3e7e1df",
					"jsonFile" : "target-imgui-MinSizeRel-3508612f063e78e6345c.json",
					"name" : "imgui",
					"projectIndex" : 0
				},
				{
					"directoryIndex" : 0,
					"id" : "imnodeflow::@6890427a1f51a3e7e1df",
					"jsonFile" : "target-imnodeflow-MinSizeRel-f9951d975e1ca37e0ee3.json",
					"name" : "imnodeflow",
					"projectIndex" : 0
				}
			]
		},
		{
			"directories" : 
			[
				{
					"build" : ".",
					"jsonFile" : "directory-.-RelWithDebInfo-d0094a50bb2071803777.json",
					"minimumCMakeVersion" : 
					{
						"string" : "3.10"
					},
					"projectIndex" : 0,
					"source" : ".",
					"targetIndexes" : 
					[
						0,
						1,
						2,
						3,
						4,
						5
					]
				}
			],
			"name" : "RelWithDebInfo",
			"projects" : 
			[
				{
					"directoryIndexes" : 
					[
						0
					],
					"name" : "Composite",
					"targetIndexes" : 
					[
						0,
						1,
						2,
						3,
						4,
						5
					]
				}
			],
			"targets" : 
			[
				{
					"directoryIndex" : 0,
					"id" : "ALL_BUILD::@6890427a1f51a3e7e1df",
					"jsonFile" : "target-ALL_BUILD-RelWithDebInfo-907168c5d66c521f6af6.json",
					"name" : "ALL_BUILD",
					"projectIndex" : 0
				},
				{
					"directoryIndex" : 0,
					"id" : "Composite::@6890427a1f51a3e7e1df",
					"jsonFile" : "target-Composite-RelWithDebInfo-d69020928b89e92cec9e.json",
					"name" : "Composite",
					"projectIndex" : 0
				},
				{
					"directoryIndex" : 0,
					"id" : "ZERO_CHECK::@6890427a1f51a3e7e1df",
					"jsonFile" : "target-ZERO_CHECK-RelWithDebInfo-467f88993c7cd49d7801.json",
					"name" : "ZERO_CHECK",
					"projectIndex" : 0
				},
				{
					"directoryIndex" : 0,
					"id" : "glad::@6890427a1f51a3e7e1df",
					"jsonFile" : "target-glad-RelWithDebInfo-06f278c3a5c3c270e607.json",
					"name" : "glad",
					"projectIndex" : 0
				},
				{
					"directoryIndex" : 0,
					"id" : "imgui::@6890427a1f51a3e7e1df",
					"jsonFile" : "target-imgui-RelWithDebInfo-90767a0894a5c008469c.json",
					"name" : "imgui",
					"projectIndex" : 0
				},
				{
					"directoryIndex" : 0,
					"id" : "imnodeflow::@6890427a1f51a3e7e1df",
					"jsonFile" : "target-imnodeflow-RelWithDebInfo-409a38a0e3df6e541aa6.json",
					"name" : "imnodeflow",
					"projectIndex" : 0
				}
			]
		}
	],
	"kind" : "codemodel",
	"paths" : 
	{
		"build" : "D:/Composite/build",
		"source" : "D:/Composite"
	},
	"version" : 
	{
		"major" : 2,
		"minor" : 7
	}
}
